yam/__init__.py
yam/yam.py
youandme/__init__.py
youandme/client.py
youandme/commands.py
youandme/server.py
youandme/stream.py
youandme/tor.py
youandme-2.0.0.data/scripts/__init__.py
youandme-2.0.0.data/scripts/yam.py
youandme-2.0.0.dist-info/LICENSE
youandme-2.0.0.dist-info/METADATA
youandme-2.0.0.dist-info/WHEEL
youandme-2.0.0.dist-info/top_level.txt
youandme-2.0.0.dist-info/RECORD
