Metadata-Version: 2.1
Name: youandme
Version: 2.0.0
Summary: Simple private data sharing via bytearrays, Tor tunneling and metadata paranoia
Home-page: http://github.com/beardog108/youandme
Author: Kevin Froman
Author-email: beardog@mailbox.org
License: UNKNOWN
Platform: UNKNOWN
Classifier: Programming Language :: Python :: 3
Classifier: License :: OSI Approved :: GNU General Public License v3 (GPLv3)
Classifier: Operating System :: OS Independent
Requires-Python: >=3.7
Requires-Dist: stem
Requires-Dist: PySocks
